szgf/__init__.py
szgf/client.py
szgf/parser.py
szgf/schemas/__init__.py
szgf/schemas/original.py
szgf/schemas/parsed.py
szgf/validator.py
szgf-0.1.5.dist-info/WHEEL
szgf-0.1.5.dist-info/METADATA
szgf-0.1.5.dist-info/RECORD
