Metadata-Version: 2.3
Name: szgf
Version: 0.1.5
Summary: ZZZ agent guides & definition of Standardized ZZZ Guide Format (SZGF)
Requires-Dist: aiofiles>=24.1.0
Requires-Dist: aiohttp>=3.12.13
Requires-Dist: hakushin-py>=0.4.11
Requires-Dist: loguru>=0.7.3
Requires-Dist: pydantic>=2.11.7
Requires-Dist: pyyaml>=6.0.2
Requires-Python: >=3.12
